kube_models/__init__.py
kube_models/_k8s_resource_base.py
kube_models/_resource_list_generics.py
kube_models/_resource_list_pep695.py
kube_models/const.py
kube_models/loader.py
kube_models/registry.py
kube_models/resource.py
kube_models/api/__init__.py
kube_models/api/io/__init__.py
kube_models/api/io/k8s/__init__.py
kube_models/api/io/k8s/apimachinery/__init__.py
kube_models/api/io/k8s/apimachinery/pkg/__init__.py
kube_models/api/io/k8s/apimachinery/pkg/apis/__init__.py
kube_models/api/io/k8s/apimachinery/pkg/apis/meta/__init__.py
kube_models/api/io/k8s/apimachinery/pkg/apis/meta/v1.py
kube_models/api_v1/__init__.py
kube_models/api_v1/io/__init__.py
kube_models/api_v1/io/k8s/__init__.py
kube_models/api_v1/io/k8s/api/__init__.py
kube_models/api_v1/io/k8s/api/authentication/__init__.py
kube_models/api_v1/io/k8s/api/authentication/v1.py
kube_models/api_v1/io/k8s/api/autoscaling/__init__.py
kube_models/api_v1/io/k8s/api/autoscaling/v1.py
kube_models/api_v1/io/k8s/api/core/__init__.py
kube_models/api_v1/io/k8s/api/core/v1.py
kube_models/api_v1/io/k8s/api/policy/__init__.py
kube_models/api_v1/io/k8s/api/policy/v1.py
kube_models/api_v1/io/k8s/apimachinery/__init__.py
kube_models/api_v1/io/k8s/apimachinery/pkg/__init__.py
kube_models/api_v1/io/k8s/apimachinery/pkg/runtime.py
kube_models/api_v1/io/k8s/apimachinery/pkg/api/__init__.py
kube_models/api_v1/io/k8s/apimachinery/pkg/api/resource.py
kube_models/api_v1/io/k8s/apimachinery/pkg/apis/__init__.py
kube_models/api_v1/io/k8s/apimachinery/pkg/apis/meta/__init__.py
kube_models/api_v1/io/k8s/apimachinery/pkg/apis/meta/v1.py
kube_models/api_v1/io/k8s/apimachinery/pkg/util/__init__.py
kube_models/api_v1/io/k8s/apimachinery/pkg/util/intstr.py
kube_models/apis/__init__.py
kube_models/apis/io/__init__.py
kube_models/apis/io/k8s/__init__.py
kube_models/apis/io/k8s/apimachinery/__init__.py
kube_models/apis/io/k8s/apimachinery/pkg/__init__.py
kube_models/apis/io/k8s/apimachinery/pkg/apis/__init__.py
kube_models-0.4.1.dist-info/METADATA
kube_models-0.4.1.dist-info/WHEEL
kube_models-0.4.1.dist-info/licenses/LICENSE
kube_models-0.4.1.dist-info/RECORD
