Metadata-Version: 2.4
Name: kube-models
Version: 0.4.1
Summary: Python dataclasses for all Kubernetes built-in resources (v1.23+)
Project-URL: Repository, https://github.com/puzl-cloud/kube-models
Author-email: Nik Paushkin <nik@puzl.cloud>
License: MIT
License-File: LICENSE
Keywords: kubernetes,kubesdk,models
Classifier: Development Status :: 5 - Production/Stable
Classifier: Intended Audience :: Developers
Classifier: License :: OSI Approved :: MIT License
Classifier: Operating System :: OS Independent
Classifier: Programming Language :: Python
Classifier: Programming Language :: Python :: 3 :: Only
Classifier: Programming Language :: Python :: 3.10
Classifier: Programming Language :: Python :: 3.11
Classifier: Programming Language :: Python :: 3.12
Classifier: Programming Language :: Python :: 3.13
Classifier: Programming Language :: Python :: 3.14
Requires-Python: >=3.10
